handsome/__init__.py
handsome/add_number.py
handsome/message.py
p40h33_test-0.31.dist-info/METADATA
p40h33_test-0.31.dist-info/WHEEL
p40h33_test-0.31.dist-info/top_level.txt
p40h33_test-0.31.dist-info/RECORD
