Metadata-Version: 2.1
Name: p40h33-test
Version: 0.31
Summary: this file author is xiefuhe
Home-page: UNKNOWN
Author: p40h33
License: UNKNOWN
Platform: UNKNOWN
